wikirepo/__init__.py
wikirepo/utils.py
wikirepo/data/__init__.py
wikirepo/data/data_utils.py
wikirepo/data/lctn_utils.py
wikirepo/data/query.py
wikirepo/data/time_utils.py
wikirepo/data/upload.py
wikirepo/data/wd_utils.py
wikirepo/data/climate/__init__.py
wikirepo/data/climate/aqi.py
wikirepo/data/climate/precipitation.py
wikirepo/data/climate/temperature.py
wikirepo/data/demographic/__init__.py
wikirepo/data/demographic/ethnic_div.py
wikirepo/data/demographic/life_expectancy.py
wikirepo/data/demographic/literacy.py
wikirepo/data/demographic/out_of_school_children.py
wikirepo/data/demographic/population.py
wikirepo/data/economic/__init__.py
wikirepo/data/economic/gdp_ppp.py
wikirepo/data/economic/gini.py
wikirepo/data/economic/inflation_rate.py
wikirepo/data/economic/median_income.py
wikirepo/data/economic/nom_gdp.py
wikirepo/data/economic/nom_gdp_per_cap.py
wikirepo/data/economic/ppp_gdp_per_cap.py
wikirepo/data/economic/total_reserves.py
wikirepo/data/economic/unemployment.py
wikirepo/data/electoral_polls/__init__.py
wikirepo/data/electoral_results/__init__.py
wikirepo/data/electoral_results/ballot_measures.py
wikirepo/data/electoral_results/pri_executive.py
wikirepo/data/electoral_results/pri_lower_house.py
wikirepo/data/electoral_results/pri_sup_executive.py
wikirepo/data/electoral_results/pri_sup_lower_house.py
wikirepo/data/electoral_results/pri_sup_upper_house.py
wikirepo/data/electoral_results/pri_upper_house.py
wikirepo/data/electoral_results/rd1_executive.py
wikirepo/data/electoral_results/rd1_lower_house.py
wikirepo/data/electoral_results/rd1_sup_executive.py
wikirepo/data/electoral_results/rd1_sup_lower_house.py
wikirepo/data/electoral_results/rd1_sup_upper_house.py
wikirepo/data/electoral_results/rd1_upper_house.py
wikirepo/data/electoral_results/rd2_executive.py
wikirepo/data/electoral_results/rd2_lower_house.py
wikirepo/data/electoral_results/rd2_sup_executive.py
wikirepo/data/electoral_results/rd2_sup_lower_house.py
wikirepo-1.0.1.dist-info/LICENSE.txt
wikirepo-1.0.1.dist-info/METADATA
wikirepo-1.0.1.dist-info/WHEEL
wikirepo-1.0.1.dist-info/top_level.txt
wikirepo-1.0.1.dist-info/RECORD
