Metadata-Version: 2.1
Name: wikirepo
Version: 1.0.1
Summary: Python based Wikidata framework for easy dataframe extraction
Home-page: https://github.com/andrewtavis/wikirepo
Author: Andrew Tavis McAllister
Author-email: andrew.t.mcallister@gmail.com
License: new BSD
Platform: UNKNOWN
Classifier: Development Status :: 5 - Production/Stable
Classifier: Intended Audience :: Developers
Classifier: Intended Audience :: Education
Classifier: Intended Audience :: Science/Research
Classifier: License :: OSI Approved :: BSD License
Classifier: Programming Language :: Python
Classifier: Programming Language :: Python :: 3
Classifier: Programming Language :: Python :: 3.6
Classifier: Programming Language :: Python :: 3.7
Classifier: Programming Language :: Python :: 3.8
Classifier: Operating System :: OS Independent
Requires-Python: >=3.6
Requires-Dist: black (>=19.10b0)
Requires-Dist: certifi (>=2020.12.5)
Requires-Dist: numpy (>=1.19.2)
Requires-Dist: packaging (>=20.9)
Requires-Dist: pandas (>=1.1.5)
Requires-Dist: pyOpenSSL (>=20.0.1)
Requires-Dist: pytest (>=6.2.2)
Requires-Dist: pytest-cov (>=2.11.1)
Requires-Dist: tqdm (>=4.56.1)
Requires-Dist: Wikidata (>=0.7.0)
